seshypy/__init__.py
seshypy/base_session.py
seshypy/session.py
seshypy/utils.py
seshypy/version.py
seshypy-0.6.2.dist-info/AUTHORS.rst
seshypy-0.6.2.dist-info/LICENSE
seshypy-0.6.2.dist-info/LICENSE.md
seshypy-0.6.2.dist-info/METADATA
seshypy-0.6.2.dist-info/WHEEL
seshypy-0.6.2.dist-info/top_level.txt
seshypy-0.6.2.dist-info/RECORD
