Metadata-Version: 2.1
Name: seshypy
Version: 0.6.2
Summary: seshypy makes API Gateway requests and API Gateway clients easy.
Platform: all
Classifier: Development Status :: 5 - Production/Stable
Classifier: Intended Audience :: Developers
Classifier: Natural Language :: English
Classifier: License :: OSI Approved :: Apache Software License
Classifier: Programming Language :: Python
Classifier: Programming Language :: Python :: 2.7
Classifier: Programming Language :: Python :: 3
Classifier: Programming Language :: Python :: 3.4
Classifier: Programming Language :: Python :: 3.5
Classifier: Programming Language :: Python :: 3.6
Classifier: Programming Language :: Python :: 3.7
Classifier: Programming Language :: Python :: 3.8
License-File: LICENSE
License-File: LICENSE.md
License-File: AUTHORS.rst
Requires-Dist: requests-sigv4 (>=0.1.6)
Requires-Dist: cachetools (>=1.1.6)
Requires-Dist: figgypy (>=0.2.0)
Requires-Dist: future
Requires-Dist: requests (>=2.21.0)
Requires-Dist: retrying (>=1.3.3)
Requires-Dist: setuptools (>=36.5.0)
